streamlit_login_auth_ui/__init__.py
streamlit_login_auth_ui/utils.py
streamlit_login_auth_ui/widgets.py
tests/__init__.py
tests/test_run.py
streamlit_login_auth_ui-0.1.0.dist-info/LICENSE
streamlit_login_auth_ui-0.1.0.dist-info/METADATA
streamlit_login_auth_ui-0.1.0.dist-info/WHEEL
streamlit_login_auth_ui-0.1.0.dist-info/top_level.txt
streamlit_login_auth_ui-0.1.0.dist-info/RECORD
