Metadata-Version: 2.1
Name: streamlit-login-auth-ui
Version: 0.1.0
Summary: A streamlit library which provides a Login/Sign-Up UI with an option to reset password, also supports cookies.
Home-page: https://github.com/GauriSP10/streamlit_login_signup_ui
Author: Gauri Prabhakar
Author-email: prabhakargauri10@gmail.com
License: UNKNOWN
Keywords: streamlit,machine learning,login,sign-up,authentication,cookies
Platform: UNKNOWN
Classifier: License :: OSI Approved :: MIT License
Classifier: Natural Language :: English
Classifier: Operating System :: OS Independent
Requires-Python: >=3.9.12
License-File: LICENSE
Requires-Dist: streamlit
Requires-Dist: streamlit-lottie
Requires-Dist: extra-streamlit-components
Requires-Dist: streamlit-option-menu
Requires-Dist: trycourier
Requires-Dist: streamlit-cookies-manager
